astro_prost/__init__.py
astro_prost/_version.py
astro_prost/associate.py
astro_prost/demo.py
astro_prost/diagnose.py
astro_prost/helpers.py
astro_prost/data/GLADE+_HyperLedaSizes_mod_withz.csv.gz
astro_prost/data/MLP_lupton.hdf5
astro_prost/data/MLP_lupton.lock
astro_prost/data/ZTFBTS_TransientTable.csv
astro_prost/data/__init__.py
astro_prost/data/panstarrs_metadata.pkl
astro_prost-1.2.13.dist-info/licenses/LICENSE
astro_prost-1.2.13.dist-info/METADATA
astro_prost-1.2.13.dist-info/WHEEL
astro_prost-1.2.13.dist-info/top_level.txt
astro_prost-1.2.13.dist-info/RECORD
