Metadata-Version: 2.4
Name: astro-prost
Version: 1.2.13
Author-email: Alex Gagliano <gaglian2@mit.edu>
License: MIT License
Project-URL: Source Code, https://github.com/alexandergagliano/prost
Classifier: Development Status :: 4 - Beta
Classifier: License :: OSI Approved :: MIT License
Classifier: Intended Audience :: Developers
Classifier: Intended Audience :: Science/Research
Classifier: Operating System :: OS Independent
Classifier: Programming Language :: Python
Requires-Python: >=3.8
License-File: LICENSE
Requires-Dist: numpy
Requires-Dist: astropy
Requires-Dist: matplotlib
Requires-Dist: pandas
Requires-Dist: scikit-learn
Requires-Dist: tqdm
Requires-Dist: scipy
Requires-Dist: specutils>=1.13; python_version == "3.9"
Requires-Dist: astro-datalab
Requires-Dist: requests
Requires-Dist: colorama
Requires-Dist: sfdmap; python_version <= "3.9"
Requires-Dist: sfdmap2; python_version >= "3.9"
Requires-Dist: filelock
Provides-Extra: dev
Requires-Dist: asv==0.6.4; extra == "dev"
Requires-Dist: jupyter; extra == "dev"
Requires-Dist: pre-commit; extra == "dev"
Requires-Dist: pytest; extra == "dev"
Requires-Dist: pytest-cov; extra == "dev"
Requires-Dist: ruff; extra == "dev"
Dynamic: license-file
